glerm-0.5.4.data/scripts/glerm
pyglerm/__init__.py
pyglerm/data/beam.png
pyglerm/data/beam_swap.ogg
pyglerm/data/blank_tile.png
pyglerm/data/blank_tile_blue.png
pyglerm/data/blank_tile_core.png
pyglerm/data/blank_tile_core_blue.png
pyglerm/data/blank_tile_core_green.png
pyglerm/data/blank_tile_core_orange.png
pyglerm/data/blank_tile_core_purple.png
pyglerm/data/blank_tile_core_red.png
pyglerm/data/blank_tile_core_white.png
pyglerm/data/blank_tile_core_yellow.png
pyglerm/data/blank_tile_green.png
pyglerm/data/blank_tile_orange.png
pyglerm/data/blank_tile_purple.png
pyglerm/data/blank_tile_red.png
pyglerm/data/blank_tile_white.png
pyglerm/data/blank_tile_yellow.png
pyglerm/data/chit_blue_sphere.png
pyglerm/data/chit_green_sphere.png
pyglerm/data/chit_red_sphere.png
pyglerm/data/chit_yellow_sphere.png
pyglerm/data/game_over.png
pyglerm/data/music.ogg
pyglerm/data/new_level.ogg
pyglerm/data/paused.png
pyglerm/data/player_blue_cone.png
pyglerm/data/player_green_cone.png
pyglerm/data/player_red_cone.png
pyglerm/data/player_yellow_cone.png
glerm-0.5.4.dist-info/LICENSE
glerm-0.5.4.dist-info/METADATA
glerm-0.5.4.dist-info/WHEEL
glerm-0.5.4.dist-info/top_level.txt
glerm-0.5.4.dist-info/RECORD
