Metadata-Version: 2.1
Name: glerm
Version: 0.5.4
Summary: A puzzle game
Home-page: https://codeberg.org/gwync/glerm
Author: Gwyn Ciesla
Author-email: gwync@protonmail.com
License: GPLv3+
Classifier: Programming Language :: Python :: 3
Classifier: License :: OSI Approved :: GNU General Public License v3 or later (GPLv3+)
Classifier: Operating System :: OS Independent
Requires-Python: >=3.8
License-File: LICENSE
Requires-Dist: pygame
